jumparound/__init__.py
jumparound/analyzer.py
jumparound/cache.py
jumparound/cli.py
jumparound/config.py
jumparound/match.py
jumparound/tui.py
jumparound-1.1.1.dist-info/entry_points.txt
jumparound-1.1.1.dist-info/WHEEL
jumparound-1.1.1.dist-info/METADATA
jumparound-1.1.1.dist-info/RECORD
